ShifenzhongMingxiang/Dockerfile
ShifenzhongMingxiang/README.md
ShifenzhongMingxiang/__init__.py
ShifenzhongMingxiang/__main__.py
ShifenzhongMingxiang/file.epub
ShifenzhongMingxiang/index.html
ShifenzhongMingxiang/css/__init__.py
ShifenzhongMingxiang/css/annotations.css
ShifenzhongMingxiang/css/main.css
ShifenzhongMingxiang/css/normalize.css
ShifenzhongMingxiang/css/popup.css
ShifenzhongMingxiang/font/__init__.py
ShifenzhongMingxiang/font/fontello.eot
ShifenzhongMingxiang/font/fontello.svg
ShifenzhongMingxiang/font/fontello.ttf
ShifenzhongMingxiang/font/fontello.woff
ShifenzhongMingxiang/img/__init__.py
ShifenzhongMingxiang/img/annotator-glyph-sprite.png
ShifenzhongMingxiang/img/annotator-icon-sprite.png
ShifenzhongMingxiang/img/apple-touch-icon.png
ShifenzhongMingxiang/img/cancelfullscreen.png
ShifenzhongMingxiang/img/close.png
ShifenzhongMingxiang/img/fullscreen.png
ShifenzhongMingxiang/img/loader.gif
ShifenzhongMingxiang/img/menu-icon.png
ShifenzhongMingxiang/img/save.png
ShifenzhongMingxiang/img/saved.png
ShifenzhongMingxiang/img/settings-s.png
ShifenzhongMingxiang/img/settings.png
ShifenzhongMingxiang/img/star.png
ShifenzhongMingxiang/js/__init__.py
ShifenzhongMingxiang/js/epub.js
ShifenzhongMingxiang/js/epub.min.js
ShifenzhongMingxiang/js/epub.min.map
ShifenzhongMingxiang/js/hooks.min.js
ShifenzhongMingxiang/js/hooks.min.map
ShifenzhongMingxiang/js/reader.js
ShifenzhongMingxiang/js/reader.js.map
ShifenzhongMingxiang/js/reader.min.js
ShifenzhongMingxiang/js/reader.min.map
ShifenzhongMingxiang/js/hooks/__init__.py
ShifenzhongMingxiang/js/hooks/extensions/__init__.py
ShifenzhongMingxiang/js/hooks/extensions/highlight.js
ShifenzhongMingxiang/js/libs/__init__.py
ShifenzhongMingxiang/js/libs/jquery.min.js
ShifenzhongMingxiang/js/libs/localforage.min.js
ShifenzhongMingxiang/js/libs/screenfull.js
ShifenzhongMingxiang/js/libs/screenfull.min.js
ShifenzhongMingxiang/js/libs/zip.min.js
ShifenzhongMingxiang/js/plugins/__init__.py
shifenzhong_mingxiang-2022.10.9.1.dist-info/METADATA
shifenzhong_mingxiang-2022.10.9.1.dist-info/WHEEL
shifenzhong_mingxiang-2022.10.9.1.dist-info/entry_points.txt
shifenzhong_mingxiang-2022.10.9.1.dist-info/top_level.txt
shifenzhong_mingxiang-2022.10.9.1.dist-info/RECORD
